instaUploadPy/__init__.py
instaUploadPy/instaUpload.py
insta_upload_py-0.0.20.dist-info/METADATA
insta_upload_py-0.0.20.dist-info/WHEEL
insta_upload_py-0.0.20.dist-info/top_level.txt
insta_upload_py-0.0.20.dist-info/RECORD
