Metadata-Version: 2.1
Name: insta-upload-py
Version: 0.0.20
Summary: A Python package to automate video uploads to Instagram at set intervals using web requests.
Author: djalti
Author-email: abdeldjalilselamnia@gmail.com
Keywords: python,instagram,upload,requests,reels,pages,bot,automation
Classifier: Development Status :: 3 - Alpha
Classifier: Intended Audience :: Developers
Classifier: Programming Language :: Python :: 3
Classifier: Operating System :: Unix
Classifier: Operating System :: MacOS :: MacOS X
Classifier: Operating System :: Microsoft :: Windows
Requires-Dist: moviepy
Requires-Dist: opencv-python
Requires-Dist: pillow
Requires-Dist: requests
